JT_AWS/__init__.py
JT_AWS/aws.py
JT_AWS/dynamo_util.py
JT_AWS/lambda_util.py
JT_AWS/pip_util.py
JT_AWS/zip_util.py
JT_AWS-0.0.15.dist-info/LICENSE
JT_AWS-0.0.15.dist-info/METADATA
JT_AWS-0.0.15.dist-info/WHEEL
JT_AWS-0.0.15.dist-info/top_level.txt
JT_AWS-0.0.15.dist-info/RECORD
