Metadata-Version: 2.1
Name: JT-AWS
Version: 0.0.15
Summary: My AWS boto3 Wrapper
Home-page: https://github.com/Gothingbop/JT_AWS
Author: Jacob Thompson
Author-email: Gothingbop@gmail.com
License: UNKNOWN
Platform: UNKNOWN
Classifier: Programming Language :: Python :: 3
Classifier: License :: OSI Approved :: MIT License
Classifier: Operating System :: OS Independent
Requires-Python: >=3
Requires-Dist: boto3
Requires-Dist: paramiko
